fhir_rdf_validator/__init__.py
fhir_rdf_validator/validate.py
fhir_rdf_validator/cache/account.shexj
fhir_rdf_validator/cache/activitydefinition.shexj
fhir_rdf_validator/cache/administrableproductdefinition.shexj
fhir_rdf_validator/cache/adverseevent.shexj
fhir_rdf_validator/cache/allergyintolerance.shexj
fhir_rdf_validator/cache/appointment.shexj
fhir_rdf_validator/cache/appointmentresponse.shexj
fhir_rdf_validator/cache/auditevent.shexj
fhir_rdf_validator/cache/basic.shexj
fhir_rdf_validator/cache/binary.shexj
fhir_rdf_validator/cache/biologicallyderivedproduct.shexj
fhir_rdf_validator/cache/bodystructure.shexj
fhir_rdf_validator/cache/bundle.shexj
fhir_rdf_validator/cache/capabilitystatement.shexj
fhir_rdf_validator/cache/capabilitystatement2.shexj
fhir_rdf_validator/cache/careplan.shexj
fhir_rdf_validator/cache/careteam.shexj
fhir_rdf_validator/cache/catalogentry.shexj
fhir_rdf_validator/cache/chargeitem.shexj
fhir_rdf_validator/cache/chargeitemdefinition.shexj
fhir_rdf_validator/cache/claim.shexj
fhir_rdf_validator/cache/claimresponse.shexj
fhir_rdf_validator/cache/clinicalimpression.shexj
fhir_rdf_validator/cache/clinicaluseissue.shexj
fhir_rdf_validator/cache/codesystem.shexj
fhir_rdf_validator/cache/communication.shexj
fhir_rdf_validator/cache/communicationrequest.shexj
fhir_rdf_validator/cache/compartmentdefinition.shexj
fhir_rdf_validator/cache/composition.shexj
fhir_rdf_validator/cache/conceptmap.shexj
fhir_rdf_validator/cache/condition.shexj
fhir_rdf_validator/cache/conditiondefinition.shexj
fhir_rdf_validator/cache/consent.shexj
fhir_rdf_validator/cache/contract.shexj
fhir_rdf_validator/cache/coverage.shexj
fhir_rdf_validator/cache/coverageeligibilityrequest.shexj
fhir_rdf_validator/cache/coverageeligibilityresponse.shexj
fhir_rdf_validator/cache/detectedissue.shexj
fhir_rdf_validator/cache/device.shexj
fhir_rdf_validator/cache/devicedefinition.shexj
fhir_rdf_validator/cache/devicemetric.shexj
fhir_rdf_validator/cache/devicerequest.shexj
fhir_rdf_validator-0.0.2.dist-info/AUTHORS
fhir_rdf_validator-0.0.2.dist-info/LICENSE
fhir_rdf_validator-0.0.2.dist-info/METADATA
fhir_rdf_validator-0.0.2.dist-info/WHEEL
fhir_rdf_validator-0.0.2.dist-info/entry_points.txt
fhir_rdf_validator-0.0.2.dist-info/pbr.json
fhir_rdf_validator-0.0.2.dist-info/top_level.txt
fhir_rdf_validator-0.0.2.dist-info/RECORD
