Metadata-Version: 2.1
Name: fhir-rdf-validator
Version: 0.0.2
Summary: FHIR RDF Validation Tool
Home-page: https://github.com/FHIRCat/fhir_rdf_validator/
Author: Harold Solbrig
Author-email: solbrig@jhu.edu
License: CC0 1.0 Universal
Keywords: fhir,rdf,shex
Platform: UNKNOWN
Classifier: Development Status :: 4 - Beta
Classifier: Environment :: Console
Classifier: Intended Audience :: Developers
Classifier: Intended Audience :: Science/Research
Classifier: Intended Audience :: Healthcare Industry
Classifier: License :: CC0 1.0 Universal (CC0 1.0) Public Domain Dedication
Classifier: Programming Language :: Python :: 3 :: Only
Classifier: Programming Language :: Python :: 3.7
Classifier: Programming Language :: Python :: 3.8
Requires-Python: >=3.7
Requires-Dist: dirlistproc (>=1.4.5)
Requires-Dist: pyshex (>=0.7.14)
Requires-Dist: rdflib (>=4.2.2)
